firehound_package/__init__.py
firehound_package/main.py
firehound_package/reports.py
firehound_package/scanner.py
firehound_scanner-2.0.0.dist-info/METADATA
firehound_scanner-2.0.0.dist-info/WHEEL
firehound_scanner-2.0.0.dist-info/entry_points.txt
firehound_scanner-2.0.0.dist-info/top_level.txt
firehound_scanner-2.0.0.dist-info/RECORD
