Metadata-Version: 2.4
Name: firehound-scanner
Version: 2.0.0
Summary: Firebase security scanner for iOS apps
Author-email: Covert Labs <firehound@covertlabs.io>
Project-URL: Homepage, https://github.com/covertlabsaus/firehound
Project-URL: Bug Reports, https://github.com/covertlabsaus/firehound/issues
Project-URL: Source, https://github.com/covertlabsaus/firehound
Project-URL: Documentation, https://firehound.covertlabs.io
Keywords: firebase,security,scanner,ios,mobile,pentesting
Classifier: Development Status :: 4 - Beta
Classifier: Intended Audience :: Developers
Classifier: Intended Audience :: System Administrators
Classifier: Topic :: Security
Classifier: Topic :: Software Development :: Testing
Classifier: License :: OSI Approved :: MIT License
Classifier: Programming Language :: Python :: 3
Classifier: Programming Language :: Python :: 3.8
Classifier: Programming Language :: Python :: 3.9
Classifier: Programming Language :: Python :: 3.10
Classifier: Programming Language :: Python :: 3.11
Classifier: Programming Language :: Python :: 3.12
Classifier: Operating System :: OS Independent
Requires-Python: >=3.8
